kiss_slam/voxel_map.py
kiss_slam/__init__.py
kiss_slam/pose_graph_optimizer.py
kiss_slam/loop_closer.py
kiss_slam/pipeline.py
kiss_slam/local_map_graph.py
kiss_slam/slam.py
kiss_slam/occupancy_mapper.py
kiss_slam/tools/__init__.py
kiss_slam/tools/cli.py
kiss_slam/tools/visualizer.py
kiss_slam/config/config.py
kiss_slam/config/__init__.py
kiss_slam/kiss_slam_pybind/kiss_slam_pybind.cpython-311-darwin.so
kiss_slam-0.0.2.dist-info/RECORD
kiss_slam-0.0.2.dist-info/WHEEL
kiss_slam-0.0.2.dist-info/entry_points.txt
kiss_slam-0.0.2.dist-info/METADATA
kiss_slam-0.0.2.dist-info/licenses/LICENSE
