Metadata-Version: 2.2
Name: kiss-slam
Version: 0.0.2
Summary: KISS-SLAM: A Simple, Robust, and Accurate 3D LiDAR SLAM System With Enhanced Generalization Capabilities
Keywords: LiDAR,SLAM,Mapping
Author-Email: Tiziano Guadagnino <frevo93@gmail.com>, Benedikt Mersch <benedikt.mersch@gmail.com>, Saurabh Gupta <saurabh.gupta1002@gmail.com>
Classifier: Intended Audience :: Developers
Classifier: Intended Audience :: Education
Classifier: Intended Audience :: Other Audience
Classifier: Intended Audience :: Science/Research
Classifier: License :: OSI Approved :: MIT License
Classifier: Operating System :: MacOS
Classifier: Operating System :: Microsoft :: Windows
Classifier: Operating System :: Unix
Classifier: Programming Language :: C++
Classifier: Programming Language :: Python :: 3
Classifier: Programming Language :: Python :: 3.8
Classifier: Programming Language :: Python :: 3.9
Classifier: Programming Language :: Python :: 3.10
Classifier: Programming Language :: Python :: 3.11
Classifier: Programming Language :: Python :: 3.12
Project-URL: Homepage, https://github.com/PRBonn/kiss-slam
Requires-Python: >=3.8
Requires-Dist: kiss-icp>=1.2.3
Requires-Dist: map_closures>=2.0.2
Requires-Dist: open3d>=0.19.0
Requires-Dist: numpy
Requires-Dist: PyYAML
Requires-Dist: pydantic>=2
Requires-Dist: tqdm
Requires-Dist: pydantic-settings
